docs/__init__.py
docs/conf.py
netssh2/__init__.py
netssh2/exceptions.py
netssh2/globals.py
netssh2/session.py
tests/__init__.py
tests/conftest.py
tests/test_basic_session.py
tests/test_logging.py
netssh2-0.1.7.dist-info/LICENSE
netssh2-0.1.7.dist-info/METADATA
netssh2-0.1.7.dist-info/WHEEL
netssh2-0.1.7.dist-info/top_level.txt
netssh2-0.1.7.dist-info/RECORD
